18_simulation_example/simulation_example.v
module simulation_example
(
	input wire clk,
	input wire btn1_n,
	output wire led_rgb_red_n
);

reg prev_btn = 1'b0;
reg [2:0] counter = 3'd0;

wire led_state;
assign led_state = (counter == 3'd6) ? 1'b1 : 1'b0;
assign led_rgb_red_n = ~led_state;

always @ (posedge clk) begin
	prev_btn <= btn1_n;
	if ((prev_btn == 1'b1) && (btn1_n == 1'b0)) begin
		counter <= (counter + 3'd1) % 3'd7;
	end else begin
		counter <= counter;
	end
end

endmodule

18_simulation_example/simulation_tb.v
`timescale 1ns/100ps

module simulation_tb (
    output reg clk = 1'b0,
    output reg switch = 1'b1,
    output wire led
);

simulation_example simex_inst(.clk(clk), .btn1_n(switch), .led_rgb_red_n(led));

initial begin
    $dumpfile("simulation_tb.vcd"); 
    $dumpvars(0, simulation_tb);

    clk <= 1'b0;
    #100; switch <= 1'b0;
    #10; switch <= 1'b1;

    #100; switch <= 1'b0;
    #10; switch <= 1'b1;

    #100; switch <= 1'b0;
    #10; switch <= 1'b1;

    #100; switch <= 1'b0;
    #10; switch <= 1'b1;

    #100; switch <= 1'b0;
    #10; switch <= 1'b1;

    #100; switch <= 1'b0;
    #10; switch <= 1'b1;

    #100; switch <= 1'b0;
    #10; switch <= 1'b1;

    #100; switch <= 1'b0;
    #10; switch <= 1'b1;

    #10000;
    $finish;
end

always begin
    #5; clk <= ~clk;
end


endmodule

18_simulation_example/simulation_tb.vcd
$date
	Fri Nov 15 02:14:24 2024
$end
$version
	Icarus Verilog
$end
$timescale
	1ps
$end
$scope module simulation_tb $end
$var wire 1 ! led $end
$var reg 1 " clk $end
$var reg 1 # switch $end
$scope module simex_inst $end
$var wire 1 # btn1_n $end
$var wire 1 " clk $end
$var wire 1 ! led_rgb_red_n $end
$var wire 1 $ led_state $end
$var reg 3 % counter [2:0] $end
$var reg 1 & prev_btn $end
$upscope $end
$upscope $end
$enddefinitions $end
$comment Show the parameter values. $end
$dumpall
$end
#0
$dumpvars
0&
b0 %
0$
1#
0"
1!
$end
#5000
1&
1"
#10000
0"
#15000
1"
#20000
0"
#25000
1"
#30000
0"
#35000
1"
#40000
0"
#45000
1"
#50000
0"
#55000
1"
#60000
0"
#65000
1"
#70000
0"
#75000
1"
#80000
0"
#85000
1"
#90000
0"
#95000
1"
#100000
0"
0#
#105000
b1 %
0&
1"
#110000
0"
1#
#115000
1&
1"
#120000
0"
#125000
1"
#130000
0"
#135000
1"
#140000
0"
#145000
1"
#150000
0"
#155000
1"
#160000
0"
#165000
1"
#170000
0"
#175000
1"
#180000
0"
#185000
1"
#190000
0"
#195000
1"
#200000
0"
#205000
1"
#210000
0"
0#
#215000
b10 %
0&
1"
#220000
0"
1#
#225000
1&
1"
#230000
0"
#235000
1"
#240000
0"
#245000
1"
#250000
0"
#255000
1"
#260000
0"
#265000
1"
#270000
0"
#275000
1"
#280000
0"
#285000
1"
#290000
0"
#295000
1"
#300000
0"
#305000
1"
#310000
0"
#315000
1"
#320000
0"
0#
#325000
b11 %
0&
1"
#330000
0"
1#
#335000
1&
1"
#340000
0"
#345000
1"
#350000
0"
#355000
1"
#360000
0"
#365000
1"
#370000
0"
#375000
1"
#380000
0"
#385000
1"
#390000
0"
#395000
1"
#400000
0"
#405000
1"
#410000
0"
#415000
1"
#420000
0"
#425000
1"
#430000
0"
0#
#435000
b100 %
0&
1"
#440000
0"
1#
#445000
1&
1"
#450000
0"
#455000
1"
#460000
0"
#465000
1"
#470000
0"
#475000
1"
#480000
0"
#485000
1"
#490000
0"
#495000
1"
#500000
0"
#505000
1"
#510000
0"
#515000
1"
#520000
0"
#525000
1"
#530000
0"
#535000
1"
#540000
0"
0#
#545000
b101 %
0&
1"
#550000
0"
1#
#555000
1&
1"
#560000
0"
#565000
1"
#570000
0"
#575000
1"
#580000
0"
#585000
1"
#590000
0"
#595000
1"
#600000
0"
#605000
1"
#610000
0"
#615000
1"
#620000
0"
#625000
1"
#630000
0"
#635000
1"
#640000
0"
#645000
1"
#650000
0"
0#
#655000
0!
1$
b110 %
0&
1"
#660000
0"
1#
#665000
1&
1"
#670000
0"
#675000
1"
#680000
0"
#685000
1"
#690000
0"
#695000
1"
#700000
0"
#705000
1"
#710000
0"
#715000
1"
#720000
0"
#725000
1"
#730000
0"
#735000
1"
#740000
0"
#745000
1"
#750000
0"
#755000
1"
#760000
0"
0#
#765000
1!
0$
b0 %
0&
1"
#770000
0"
1#
#775000
1&
1"
#780000
0"
#785000
1"
#790000
0"
#795000
1"
#800000
0"
#805000
1"
#810000
0"
#815000
1"
#820000
0"
#825000
1"
#830000
0"
#835000
1"
#840000
0"
#845000
1"
#850000
0"
#855000
1"
#860000
0"
#865000
1"
#870000
0"
0#
#875000
b1 %
0&
1"
#880000
0"
1#
#885000
1&
1"
